manage.py
wsgi.py
MuffinService-0.1.dev1.dist-info/DESCRIPTION.rst
MuffinService-0.1.dev1.dist-info/LICENSE.txt
MuffinService-0.1.dev1.dist-info/METADATA
MuffinService-0.1.dev1.dist-info/RECORD
MuffinService-0.1.dev1.dist-info/WHEEL
MuffinService-0.1.dev1.dist-info/metadata.json
MuffinService-0.1.dev1.dist-info/top_level.txt
muffin/__init__.py
muffin/backend.py
muffin/conftest.py
muffin/database.py
muffin/factories.py
muffin/muffin_error.py
muffin/tables.py
muffin/manage/__init__.py
muffin/manage/seed.py
muffin/v2/__init__.py
