Metadata-Version: 2.0
Name: MuffinService
Version: 0.1.dev1
Summary: Muffin is a solution for structured test result reporting
Home-page: UNKNOWN
Author: UNKNOWN
Author-email: UNKNOWN
License: UNKNOWN
Platform: UNKNOWN
Classifier: Development Status :: 3 - Alpha
Classifier: Programming Language :: Python :: 3.5
Requires-Dist: Flask
Requires-Dist: jsonschema
Requires-Dist: Flask-Script
Requires-Dist: fake-factory
Requires-Dist: jsonpatch
Requires-Dist: Flask-SQLAlchemy
